drone_api_client/__init__.py
drone_api_client/category.py
drone_api_client/drone_api_client.py
drone_api_client/service.py
drone_api_client/session.py
drone_api_client/model/__init__.py
drone_api_client/model/build.py
drone_api_client/model/cron.py
drone_api_client/model/repos.py
drone_api_client/model/secrets.py
drone_api_client/model/template.py
drone_api_client/model/user.py
drone_api_client/model/users.py
drone_api_client-0.2.3.dist-info/LICENSE
drone_api_client-0.2.3.dist-info/METADATA
drone_api_client-0.2.3.dist-info/WHEEL
drone_api_client-0.2.3.dist-info/entry_points.txt
drone_api_client-0.2.3.dist-info/top_level.txt
drone_api_client-0.2.3.dist-info/RECORD
