Metadata-Version: 2.1
Name: drone-api-client
Version: 0.2.3
Summary: Drone Api Python Client
Home-page: https://github.com/Slamnlc/drone-api-client
Author: Biriukov Maksym
Author-email: maximbirukov77@gmail.com
License: UNKNOWN
Download-URL: https://github.com/Slamnlc/drone-api-client/archive/refs/tags/v0.2.3.tar.gz
Platform: UNKNOWN
License-File: LICENSE
Requires-Dist: requests
